dp_nacos_mcp_wrapper/__init__.py
dp_nacos_mcp_wrapper/server/__init__.py
dp_nacos_mcp_wrapper/server/mcp_server_info.py
dp_nacos_mcp_wrapper/server/nacos_mcp.py
dp_nacos_mcp_wrapper/server/nacos_server.py
dp_nacos_mcp_wrapper/server/nacos_settings.py
dp_nacos_mcp_wrapper/server/utils.py
dp_nacos_mcp_wrapper-0.6.0.dist-info/LICENSE
dp_nacos_mcp_wrapper-0.6.0.dist-info/METADATA
dp_nacos_mcp_wrapper-0.6.0.dist-info/WHEEL
dp_nacos_mcp_wrapper-0.6.0.dist-info/RECORD
