Metadata-Version: 2.3
Name: dp-nacos-mcp-wrapper
Version: 0.6.0
Summary: Python sdk support mcp server auto register to nacos
License: Apache-2.0
Author: xyq043170
Author-email: xyq043170@qq.com
Requires-Python: >=3.10,<4.0
Classifier: License :: OSI Approved :: Apache Software License
Classifier: Operating System :: OS Independent
Classifier: Programming Language :: Python
Classifier: Programming Language :: Python :: 3
Classifier: Programming Language :: Python :: 3.10
Classifier: Programming Language :: Python :: 3.11
Classifier: Programming Language :: Python :: 3.12
Classifier: Programming Language :: Python :: 3.13
Classifier: Topic :: Software Development :: Libraries :: Python Modules
Requires-Dist: anyio (==4.9.0)
Requires-Dist: jsonref (==1.1.0)
Requires-Dist: mcp (==1.9.2)
Requires-Dist: nacos-sdk-python (==2.0.4)
Requires-Dist: pydantic (==2.11.3)
Requires-Dist: pydantic-settings (==2.9.1)
Requires-Dist: uvicorn (==0.34.2)
